LICENSE
MANIFEST.in
README.rst
setup.py
chembl_business_model/__init__.py
chembl_business_model/exceptions.py
chembl_business_model/indigoWrapper.py
chembl_business_model/listeners.py
chembl_business_model/signals.py
chembl_business_model/tasks.py
chembl_business_model/tests.py
chembl_business_model/utils.py
chembl_business_model.egg-info/PKG-INFO
chembl_business_model.egg-info/SOURCES.txt
chembl_business_model.egg-info/dependency_links.txt
chembl_business_model.egg-info/not-zip-safe
chembl_business_model.egg-info/requires.txt
chembl_business_model.egg-info/top_level.txt
chembl_business_model/models/__init__.py
chembl_business_model/models/approvedDrugData.py
chembl_business_model/models/bindingSiteInformation.py
chembl_business_model/models/compounds.py
chembl_business_model/models/experimentalData.py
chembl_business_model/models/general.py
chembl_business_model/models/mechanismAnnotation.py
chembl_business_model/models/meta.py
chembl_business_model/models/sourceInformation.py
chembl_business_model/models/targetInformation.py